pyparse_client/__init__.py
pyparse_client/_client.py
pyparse_client/_constants.py
pyparse_client/_types.py
pyparse_client/pyparse.py
pyparse_client/utils.py
pyparse_client-0.1.0.dist-info/METADATA
pyparse_client-0.1.0.dist-info/WHEEL
pyparse_client-0.1.0.dist-info/RECORD
